Metadata-Version: 2.1
Name: django-simplecms
Version: 1.1.3
Summary: Simple Django-based CMS
Author-email: Jaap Joris Vens <jj@rtts.eu>
Project-URL: Changelog, https://github.com/rtts/django-simplecms/releases/
Project-URL: Issues, https://github.com/rtts/django-simplecms/issues/
Project-URL: Source, https://github.com/rtts/django-simplecms/
Classifier: Framework :: Django
Classifier: License :: OSI Approved :: GNU General Public License v3 or later (GPLv3+)
Classifier: Operating System :: OS Independent
Classifier: Programming Language :: Python
Requires-Python: >=3.8
License-File: LICENSE
Requires-Dist: django
Requires-Dist: django-embed-video
Requires-Dist: django-tidy
Requires-Dist: easy-thumbnails
Requires-Dist: libsass
Requires-Dist: markdown
Requires-Dist: psycopg
Requires-Dist: pylibmc
